griff/__init__.py
griff/appli/__init__.py
griff/appli/app_event/__init__.py
griff/appli/app_event/app_event.py
griff/appli/app_event/app_event_bus.py
griff/appli/app_event/app_event_dispatcher.py
griff/appli/app_event/app_event_handler.py
griff/appli/app_event/middlewares/__init__.py
griff/appli/app_event/middlewares/app_event_logger_middleware.py
griff/appli/command/__init__.py
griff/appli/command/command.py
griff/appli/command/command_bus.py
griff/appli/command/command_dispatcher.py
griff/appli/command/command_handler.py
griff/appli/command/command_middleware.py
griff/appli/command/middlewares/__init__.py
griff/appli/command/middlewares/command_app_event_dispatch_middleware.py
griff/appli/command/middlewares/command_event_dispatch_middleware.py
griff/appli/command/middlewares/command_logger_middleware.py
griff/appli/command/middlewares/command_uow_middleware.py
griff/appli/event/__init__.py
griff/appli/event/event.py
griff/appli/event/event_bus.py
griff/appli/event/event_dispatcher.py
griff/appli/event/event_handler.py
griff/appli/event/event_middleware.py
griff/appli/event/middlewares/__init__.py
griff/appli/event/middlewares/event_logger_middleware.py
griff/appli/message/__init__.py
griff/appli/message/message.py
griff/appli/message/message_bus.py
griff/appli/message/message_dispatcher.py
griff/appli/message/message_handler.py
griff/appli/message/message_middleware.py
griff/appli/policies/__init__.py
griff/appli/policies/policy.py
griff/appli/policies/resource_must_exist_policy.py
griff/appli/policies/resource_must_not_exist_policy.py
griff/appli/query/__init__.py
griff/appli/query/middlewares/__init__.py
griff/appli/query/middlewares/query_logger_middleware.py
griff/appli/query/query.py
griff/appli/query/query_bus.py
griff/appli/query/query_dispatcher.py
griff/appli/query/query_handler.py
griff/appli/query/query_middleware.py
griff/context_entry_point.py
griff/domain/__init__.py
griff/domain/common_types.py
griff/domain/vo/__init__.py
griff/domain/vo/money.py
griffv2-2.0.28.dist-info/LICENCE.md
griffv2-2.0.28.dist-info/METADATA
griffv2-2.0.28.dist-info/WHEEL
griffv2-2.0.28.dist-info/RECORD
