Metadata-Version: 2.3
Name: griffv2
Version: 2.0.28
Summary: DDD Library
License: MIT
Author: Wedge Digital
Requires-Python: >=3.12,<4.0
Classifier: License :: OSI Approved :: MIT License
Classifier: Programming Language :: Python :: 3
Classifier: Programming Language :: Python :: 3.12
Classifier: Programming Language :: Python :: 3.13
Requires-Dist: aiosql (>=13,<14)
Requires-Dist: argon2-cffi (>=23,<24)
Requires-Dist: arrow (>=1.3,<2.0)
Requires-Dist: asyncpg (>=0.30,<0.31)
Requires-Dist: cookiecutter (>=2.6.0,<3.0.0)
Requires-Dist: email-validator (>=2,<3)
Requires-Dist: fastapi (>=0.115,<0.116)
Requires-Dist: fastapi-babel (>=1,<2)
Requires-Dist: httpx (>=0.28.1,<0.29.0)
Requires-Dist: injector (>=0.22,<0.23)
Requires-Dist: loguru (>=0.7,<0.8)
Requires-Dist: orjson (>=3.10,<4.0)
Requires-Dist: psycopg2-binary (>=2.9,<3.0)
Requires-Dist: pydantic (>=2,<3)
Requires-Dist: pydantic-i18n (>=0.4,<0.5)
Requires-Dist: pydantic-settings (>=2,<3)
Requires-Dist: pyjwt (>=2.9,<3.0)
Requires-Dist: python-multipart (>=0.0.20,<0.0.21)
Requires-Dist: python-ulid[pydantic] (>=3,<4)
Requires-Dist: typer (>=0.15,<0.16)
Requires-Dist: yoyo-migrations (>=9,<10)
Project-URL: Repository, https://github.com/Wedge-Digital/griff
